safelife/__init__.py
safelife/__main__.py
safelife/env_wrappers.py
safelife/file_finder.py
safelife/helper_utils.py
safelife/interactive_game.py
safelife/keyboard_input.py
safelife/level_iterator.py
safelife/proc_gen.py
safelife/random.py
safelife/render_graphics.py
safelife/render_text.py
safelife/safelife_env.py
safelife/safelife_game.py
safelife/safelife_logger.py
safelife/side_effects.py
safelife/speedups.abi3.so
safelife/sprites.png
safelife/levels/benchmarks/v0.1/append-dynamic-1.npz
safelife/levels/benchmarks/v0.1/append-dynamic-2.npz
safelife/levels/benchmarks/v0.1/append-dynamic-3.npz
safelife/levels/benchmarks/v0.1/append-dynamic-4.npz
safelife/levels/benchmarks/v0.1/append-still-1.npz
safelife/levels/benchmarks/v0.1/append-still-2.npz
safelife/levels/benchmarks/v0.1/append-still-3.npz
safelife/levels/benchmarks/v0.1/append-still-4.npz
safelife/levels/benchmarks/v0.1/append-stochastic-1.npz
safelife/levels/benchmarks/v0.1/append-stochastic-2.npz
safelife/levels/benchmarks/v0.1/append-stochastic-3.npz
safelife/levels/benchmarks/v0.1/append-stochastic-4.npz
safelife/levels/benchmarks/v0.1/append-stochastic-osc-1.npz
safelife/levels/benchmarks/v0.1/append-stochastic-osc-2.npz
safelife/levels/benchmarks/v0.1/bipole.npz
safelife/levels/benchmarks/v0.1/box-side-effect.npz
safelife/levels/benchmarks/v0.1/prune-dynamic-1.npz
safelife/levels/benchmarks/v0.1/prune-dynamic-2.npz
safelife/levels/benchmarks/v0.1/prune-dynamic-3.npz
safelife/levels/benchmarks/v0.1/prune-dynamic-4.npz
safelife/levels/benchmarks/v0.1/prune-still-1.npz
safelife/levels/benchmarks/v0.1/prune-still-2.npz
safelife/levels/benchmarks/v0.1/prune-still-3.npz
safelife/levels/benchmarks/v0.1/prune-still-4.npz
safelife/levels/benchmarks/v0.1/prune-stochastic-1.npz
safelife/levels/benchmarks/v0.1/prune-stochastic-2.npz
safelife/levels/benchmarks/v0.1/prune-stochastic-3.npz
safelife/levels/benchmarks/v0.1/prune-stochastic-4.npz
safelife/levels/benchmarks/v0.1/prune-stochastic-osc-1.npz
safelife-1.2.2.dist-info/LICENSE
safelife-1.2.2.dist-info/METADATA
safelife-1.2.2.dist-info/WHEEL
safelife-1.2.2.dist-info/entry_points.txt
safelife-1.2.2.dist-info/top_level.txt
safelife-1.2.2.dist-info/RECORD
