Metadata-Version: 2.1
Name: safelife
Version: 1.2.2
Summary: Safety benchmarks for reinforcement learning
Home-page: https://github.com/PartnershipOnAI/safelife
Author: Carroll L. Wainwright
Author-email: carroll@partnershiponai.org
License: UNKNOWN
Platform: UNKNOWN
Classifier: Programming Language :: Python :: 3
Classifier: License :: OSI Approved :: Apache Software License
Classifier: Operating System :: OS Independent
Classifier: Topic :: Scientific/Engineering :: Artificial Intelligence
Requires-Dist: pyemd (==0.5.1)
Requires-Dist: numpy (>=1.18.0)
Requires-Dist: scipy (>=1.0.0)
Requires-Dist: gym (>=0.12.5)
Requires-Dist: imageio (>=2.5.0)
Requires-Dist: pyglet (<=1.5.0,>=1.3.2)
Requires-Dist: pyyaml (>=3.12)
